{
	"info": {
		"_postman_id": "ca5bf2e6-baa8-478b-ad71-f0056ab0c50c",
		"name": "orderApi",
		"schema": "https://schema.getpostman.com/json/collection/v2.1.0/collection.json",
		"_exporter_id": "29210119"
	},
	"item": [
		{
			"name": "create order",
			"request": {
				"method": "POST",
				"header": [],
				"body": {
					"mode": "raw",
					"raw": "{\r\n     \"orderItems\":[{\"_id\":\"653a6e995779169ab6a163fc\",\"quantity\":2},{\"_id\":\"653aa255accc6e36775ff2a1\",\"quantity\":1},{\"_id\":\"653a9dddaccc6e36775ff295\",\"quantity\":1}],\r\n     \"addressId\":\"653b7c80f54a7676d5e14407\"\r\n}",
					"options": {
						"raw": {
							"language": "json"
						}
					}
				},
				"url": {
					"raw": "{{orderUrl}}",
					"host": [
						"{{orderUrl}}"
					]
				}
			},
			"response": [
				{
					"name": "Successfully creating order",
					"originalRequest": {
						"method": "POST",
						"header": [],
						"body": {
							"mode": "raw",
							"raw": "{\r\n     \"orderItems\":[{\"_id\":\"653a71545779169ab6a1640b\",\"quantity\":1},{\"_id\":\"653aa255accc6e36775ff2a1\",\"quantity\":1}],\r\n     \"addressId\":\"653aa5a6accc6e36775ff2a3\"\r\n}",
							"options": {
								"raw": {
									"language": "json"
								}
							}
						},
						"url": {
							"raw": "{{orderUrl}}",
							"host": [
								"{{orderUrl}}"
							]
						}
					},
					"status": "OK",
					"code": 200,
					"_postman_previewlanguage": "plain",
					"header": [
						{
							"key": "X-Powered-By",
							"value": "Express"
						},
						{
							"key": "Access-Control-Allow-Origin",
							"value": "*"
						},
						{
							"key": "Access-Control-Allow-Methods",
							"value": "OPTIONS, GET, POST, PUT, PATCH, DELETE"
						},
						{
							"key": "Access-Control-Allow-Headers",
							"value": "Content-Type, Authorization"
						},
						{
							"key": "Date",
							"value": "Fri, 27 Oct 2023 07:51:40 GMT"
						},
						{
							"key": "Connection",
							"value": "keep-alive"
						},
						{
							"key": "Keep-Alive",
							"value": "timeout=5"
						},
						{
							"key": "Content-Length",
							"value": "0"
						}
					],
					"cookie": [],
					"body": null
				},
				{
					"name": "branch not found",
					"originalRequest": {
						"method": "POST",
						"header": [],
						"body": {
							"mode": "raw",
							"raw": "{\r\n     \"orderItems\":[{\"_id\":\"653a6e995779169ab6a163fc\",\"quantity\":2},{\"_id\":\"653aa255accc6e36775ff2a1\",\"quantity\":1},{\"_id\":\"653a9dddaccc6e36775ff295\",\"quantity\":1}],\r\n     \"addressId\":\"653b7c80f54a7676d5e14407\"\r\n}",
							"options": {
								"raw": {
									"language": "json"
								}
							}
						},
						"url": {
							"raw": "{{orderUrl}}",
							"host": [
								"{{orderUrl}}"
							]
						}
					},
					"status": "Not Found",
					"code": 404,
					"_postman_previewlanguage": "json",
					"header": [
						{
							"key": "X-Powered-By",
							"value": "Express"
						},
						{
							"key": "Access-Control-Allow-Origin",
							"value": "*"
						},
						{
							"key": "Access-Control-Allow-Methods",
							"value": "OPTIONS, GET, POST, PUT, PATCH, DELETE"
						},
						{
							"key": "Access-Control-Allow-Headers",
							"value": "Content-Type, Authorization"
						},
						{
							"key": "Content-Type",
							"value": "application/json; charset=utf-8"
						},
						{
							"key": "Content-Length",
							"value": "66"
						},
						{
							"key": "ETag",
							"value": "W/\"42-fMGExwcek17+Pa+TVAlCRgHirv4\""
						},
						{
							"key": "Date",
							"value": "Fri, 27 Oct 2023 09:02:42 GMT"
						},
						{
							"key": "Connection",
							"value": "keep-alive"
						},
						{
							"key": "Keep-Alive",
							"value": "timeout=5"
						}
					],
					"cookie": [],
					"body": "{\n    \"message\": \"Sorry we don't have any brand close to your location\"\n}"
				},
				{
					"name": "item not found",
					"originalRequest": {
						"method": "POST",
						"header": [],
						"body": {
							"mode": "raw",
							"raw": "{\r\n     \"orderItems\":[{\"_id\":\"653a6e995779169ab6a163fe\",\"quantity\":2},{\"_id\":\"653aa255accc6e36775ff2a1\",\"quantity\":1},{\"_id\":\"653a9dddaccc6e36775ff295\",\"quantity\":1}],\r\n     \"addressId\":\"653b7c80f54a7676d5e14407\"\r\n}",
							"options": {
								"raw": {
									"language": "json"
								}
							}
						},
						"url": {
							"raw": "{{orderUrl}}",
							"host": [
								"{{orderUrl}}"
							]
						}
					},
					"status": "Not Found",
					"code": 404,
					"_postman_previewlanguage": "json",
					"header": [
						{
							"key": "X-Powered-By",
							"value": "Express"
						},
						{
							"key": "Access-Control-Allow-Origin",
							"value": "*"
						},
						{
							"key": "Access-Control-Allow-Methods",
							"value": "OPTIONS, GET, POST, PUT, PATCH, DELETE"
						},
						{
							"key": "Access-Control-Allow-Headers",
							"value": "Content-Type, Authorization"
						},
						{
							"key": "Content-Type",
							"value": "application/json; charset=utf-8"
						},
						{
							"key": "Content-Length",
							"value": "27"
						},
						{
							"key": "ETag",
							"value": "W/\"1b-UKTuPdpTNVb1jBlDXHLaorDyRrs\""
						},
						{
							"key": "Date",
							"value": "Fri, 27 Oct 2023 09:03:18 GMT"
						},
						{
							"key": "Connection",
							"value": "keep-alive"
						},
						{
							"key": "Keep-Alive",
							"value": "timeout=5"
						}
					],
					"cookie": [],
					"body": "{\n    \"message\": \"No item found\"\n}"
				},
				{
					"name": "address not found",
					"originalRequest": {
						"method": "POST",
						"header": [],
						"body": {
							"mode": "raw",
							"raw": "{\r\n     \"orderItems\":[{\"_id\":\"653a6e995779169ab6a163fc\",\"quantity\":2},{\"_id\":\"653aa255accc6e36775ff2a1\",\"quantity\":1},{\"_id\":\"653a9dddaccc6e36775ff295\",\"quantity\":1}],\r\n     \"addressId\":\"653b7c80f54a7676d5e14406\"\r\n}",
							"options": {
								"raw": {
									"language": "json"
								}
							}
						},
						"url": {
							"raw": "{{orderUrl}}",
							"host": [
								"{{orderUrl}}"
							]
						}
					},
					"status": "Not Found",
					"code": 404,
					"_postman_previewlanguage": "json",
					"header": [
						{
							"key": "X-Powered-By",
							"value": "Express"
						},
						{
							"key": "Access-Control-Allow-Origin",
							"value": "*"
						},
						{
							"key": "Access-Control-Allow-Methods",
							"value": "OPTIONS, GET, POST, PUT, PATCH, DELETE"
						},
						{
							"key": "Access-Control-Allow-Headers",
							"value": "Content-Type, Authorization"
						},
						{
							"key": "Content-Type",
							"value": "application/json; charset=utf-8"
						},
						{
							"key": "Content-Length",
							"value": "30"
						},
						{
							"key": "ETag",
							"value": "W/\"1e-noivKNlt3rQzTeZEIGZ5BsJWuQw\""
						},
						{
							"key": "Date",
							"value": "Fri, 27 Oct 2023 09:06:47 GMT"
						},
						{
							"key": "Connection",
							"value": "keep-alive"
						},
						{
							"key": "Keep-Alive",
							"value": "timeout=5"
						}
					],
					"cookie": [],
					"body": "{\n    \"message\": \"No Address found\"\n}"
				},
				{
					"name": "validation failed",
					"originalRequest": {
						"method": "POST",
						"header": [],
						"body": {
							"mode": "raw",
							"raw": "{\r\n     \"orderItems\":[{\"_id\":\"653a6e995779169ab6a163fc\",\"quantity\":2},{\"_id\":\"653aa255accc6e36775ff2a1\",\"quantity\":1},{\"_id\":\"653a9dddaccc6e36775ff295\",\"quantity\":0}],\r\n     \"addressId\":\"653b7c80f54a7676d5e14407\"\r\n}",
							"options": {
								"raw": {
									"language": "json"
								}
							}
						},
						"url": {
							"raw": "{{orderUrl}}",
							"host": [
								"{{orderUrl}}"
							]
						}
					},
					"status": "Bad Request",
					"code": 400,
					"_postman_previewlanguage": "json",
					"header": [
						{
							"key": "X-Powered-By",
							"value": "Express"
						},
						{
							"key": "Access-Control-Allow-Origin",
							"value": "*"
						},
						{
							"key": "Access-Control-Allow-Methods",
							"value": "OPTIONS, GET, POST, PUT, PATCH, DELETE"
						},
						{
							"key": "Access-Control-Allow-Headers",
							"value": "Content-Type, Authorization"
						},
						{
							"key": "Content-Type",
							"value": "application/json; charset=utf-8"
						},
						{
							"key": "Content-Length",
							"value": "31"
						},
						{
							"key": "ETag",
							"value": "W/\"1f-hXr48JXw9+c1abn9e3ChGFhAs70\""
						},
						{
							"key": "Date",
							"value": "Fri, 27 Oct 2023 09:07:59 GMT"
						},
						{
							"key": "Connection",
							"value": "keep-alive"
						},
						{
							"key": "Keep-Alive",
							"value": "timeout=5"
						}
					],
					"cookie": [],
					"body": "{\n    \"message\": \"Validation Failed\"\n}"
				}
			]
		},
		{
			"name": "get orders",
			"request": {
				"method": "GET",
				"header": [],
				"url": {
					"raw": "{{orderUrl}}/list",
					"host": [
						"{{orderUrl}}"
					],
					"path": [
						"list"
					]
				}
			},
			"response": [
				{
					"name": "get all orders",
					"originalRequest": {
						"method": "GET",
						"header": [],
						"url": {
							"raw": "{{orderUrl}}/list",
							"host": [
								"{{orderUrl}}"
							],
							"path": [
								"list"
							]
						}
					},
					"status": "OK",
					"code": 200,
					"_postman_previewlanguage": "json",
					"header": [
						{
							"key": "X-Powered-By",
							"value": "Express"
						},
						{
							"key": "Access-Control-Allow-Origin",
							"value": "*"
						},
						{
							"key": "Access-Control-Allow-Methods",
							"value": "OPTIONS, GET, POST, PUT, PATCH, DELETE"
						},
						{
							"key": "Access-Control-Allow-Headers",
							"value": "Content-Type, Authorization"
						},
						{
							"key": "Content-Type",
							"value": "application/json; charset=utf-8"
						},
						{
							"key": "Content-Length",
							"value": "866"
						},
						{
							"key": "ETag",
							"value": "W/\"362-NVQFFeM1EvxliaK4HM0PrfohmGw\""
						},
						{
							"key": "Date",
							"value": "Fri, 27 Oct 2023 07:55:39 GMT"
						},
						{
							"key": "Connection",
							"value": "keep-alive"
						},
						{
							"key": "Keep-Alive",
							"value": "timeout=5"
						}
					],
					"cookie": [],
					"body": "[\n    {\n        \"_id\": \"653b6acbf54a7676d5e143b7\",\n        \"orderItems\": [\n            {\n                \"_id\": \"653a6fe75779169ab6a16405\",\n                \"quantity\": 1,\n                \"itemName\": \"Grilled Salmon\"\n            },\n            {\n                \"_id\": \"653a9e2daccc6e36775ff298\",\n                \"quantity\": 1,\n                \"itemName\": \"Cheesecake\"\n            },\n            {\n                \"_id\": \"653aa157accc6e36775ff29e\",\n                \"quantity\": 2,\n                \"itemName\": \"Ice Tea\"\n            }\n        ],\n        \"userId\": \"6539fae9bc694f8bcfce6629\",\n        \"addressId\": \"653aa5a6accc6e36775ff2a3\",\n        \"branchId\": \"653b61e2f54a7676d5e14394\",\n        \"status\": \"pending\",\n        \"totalPrice\": 31,\n        \"dateOrdered\": \"2023-10-27T06:47:09.513Z\",\n        \"__v\": 0\n    },\n    {\n        \"_id\": \"653b6c0cf54a7676d5e143bd\",\n        \"orderItems\": [\n            {\n                \"_id\": \"653a71545779169ab6a1640b\",\n                \"quantity\": 1,\n                \"itemName\": \"Chicken Alfredo Pasta\"\n            },\n            {\n                \"_id\": \"653aa255accc6e36775ff2a1\",\n                \"quantity\": 1,\n                \"itemName\": \"Coca-Cola\"\n            }\n        ],\n        \"userId\": \"6539fae9bc694f8bcfce6629\",\n        \"addressId\": \"653aa5a6accc6e36775ff2a3\",\n        \"branchId\": \"653b61e2f54a7676d5e14394\",\n        \"status\": \"pending\",\n        \"totalPrice\": 18,\n        \"dateOrdered\": \"2023-10-27T06:47:09.513Z\",\n        \"__v\": 0\n    }\n]"
				}
			]
		},
		{
			"name": "get order",
			"request": {
				"method": "GET",
				"header": []
			},
			"response": [
				{
					"name": "correct orderId",
					"originalRequest": {
						"method": "GET",
						"header": [],
						"url": {
							"raw": "{{orderUrl}}/details?orderId=653b6acbf54a7676d5e143b7",
							"host": [
								"{{orderUrl}}"
							],
							"path": [
								"details"
							],
							"query": [
								{
									"key": "orderId",
									"value": "653b6acbf54a7676d5e143b7"
								}
							]
						}
					},
					"status": "OK",
					"code": 200,
					"_postman_previewlanguage": "json",
					"header": [
						{
							"key": "X-Powered-By",
							"value": "Express"
						},
						{
							"key": "Access-Control-Allow-Origin",
							"value": "*"
						},
						{
							"key": "Access-Control-Allow-Methods",
							"value": "OPTIONS, GET, POST, PUT, PATCH, DELETE"
						},
						{
							"key": "Access-Control-Allow-Headers",
							"value": "Content-Type, Authorization"
						},
						{
							"key": "Content-Type",
							"value": "application/json; charset=utf-8"
						},
						{
							"key": "Content-Length",
							"value": "475"
						},
						{
							"key": "ETag",
							"value": "W/\"1db-lzSoW2cD7vkKBnRbAN/OomEhGJs\""
						},
						{
							"key": "Date",
							"value": "Fri, 27 Oct 2023 08:13:21 GMT"
						},
						{
							"key": "Connection",
							"value": "keep-alive"
						},
						{
							"key": "Keep-Alive",
							"value": "timeout=5"
						}
					],
					"cookie": [],
					"body": "{\n    \"_id\": \"653b6acbf54a7676d5e143b7\",\n    \"orderItems\": [\n        {\n            \"_id\": \"653a6fe75779169ab6a16405\",\n            \"quantity\": 1,\n            \"itemName\": \"Grilled Salmon\"\n        },\n        {\n            \"_id\": \"653a9e2daccc6e36775ff298\",\n            \"quantity\": 1,\n            \"itemName\": \"Cheesecake\"\n        },\n        {\n            \"_id\": \"653aa157accc6e36775ff29e\",\n            \"quantity\": 2,\n            \"itemName\": \"Ice Tea\"\n        }\n    ],\n    \"userId\": \"6539fae9bc694f8bcfce6629\",\n    \"status\": \"pending\",\n    \"totalPrice\": 31,\n    \"dateOrdered\": \"2023-10-27T06:47:09.513Z\",\n    \"userEmail\": \"mounayercharbel07@gmail.com\",\n    \"userAddress\": \"zook mosbeh\",\n    \"branchName\": \"Zook Branch\"\n}"
				},
				{
					"name": "forbidden error",
					"originalRequest": {
						"method": "GET",
						"header": [],
						"url": {
							"raw": "{{orderUrl}}/details?orderId=653b6acbf54a7676d5e143b7",
							"host": [
								"{{orderUrl}}"
							],
							"path": [
								"details"
							],
							"query": [
								{
									"key": "orderId",
									"value": "653b6acbf54a7676d5e143b7"
								}
							]
						}
					},
					"status": "Forbidden",
					"code": 403,
					"_postman_previewlanguage": "json",
					"header": [
						{
							"key": "X-Powered-By",
							"value": "Express"
						},
						{
							"key": "Access-Control-Allow-Origin",
							"value": "*"
						},
						{
							"key": "Access-Control-Allow-Methods",
							"value": "OPTIONS, GET, POST, PUT, PATCH, DELETE"
						},
						{
							"key": "Access-Control-Allow-Headers",
							"value": "Content-Type, Authorization"
						},
						{
							"key": "Content-Type",
							"value": "application/json; charset=utf-8"
						},
						{
							"key": "Content-Length",
							"value": "23"
						},
						{
							"key": "ETag",
							"value": "W/\"17-t66ykm1tLqNPfWDnZa+sQL1+4+c\""
						},
						{
							"key": "Date",
							"value": "Fri, 27 Oct 2023 08:14:40 GMT"
						},
						{
							"key": "Connection",
							"value": "keep-alive"
						},
						{
							"key": "Keep-Alive",
							"value": "timeout=5"
						}
					],
					"cookie": [],
					"body": "{\n    \"message\": \"forbidden\"\n}"
				},
				{
					"name": "no order found error",
					"originalRequest": {
						"method": "GET",
						"header": [],
						"url": {
							"raw": "{{orderUrl}}/details?orderId=653b6acbf54a7676d5e143b6",
							"host": [
								"{{orderUrl}}"
							],
							"path": [
								"details"
							],
							"query": [
								{
									"key": "orderId",
									"value": "653b6acbf54a7676d5e143b6"
								}
							]
						}
					},
					"status": "Not Found",
					"code": 404,
					"_postman_previewlanguage": "json",
					"header": [
						{
							"key": "X-Powered-By",
							"value": "Express"
						},
						{
							"key": "Access-Control-Allow-Origin",
							"value": "*"
						},
						{
							"key": "Access-Control-Allow-Methods",
							"value": "OPTIONS, GET, POST, PUT, PATCH, DELETE"
						},
						{
							"key": "Access-Control-Allow-Headers",
							"value": "Content-Type, Authorization"
						},
						{
							"key": "Content-Type",
							"value": "application/json; charset=utf-8"
						},
						{
							"key": "Content-Length",
							"value": "28"
						},
						{
							"key": "ETag",
							"value": "W/\"1c-+hiLJvFs9Ooq3CfFkj9QhVmOmnE\""
						},
						{
							"key": "Date",
							"value": "Fri, 27 Oct 2023 08:15:07 GMT"
						},
						{
							"key": "Connection",
							"value": "keep-alive"
						},
						{
							"key": "Keep-Alive",
							"value": "timeout=5"
						}
					],
					"cookie": [],
					"body": "{\n    \"message\": \"No Order found\"\n}"
				},
				{
					"name": "validation failed",
					"originalRequest": {
						"method": "GET",
						"header": [],
						"url": {
							"raw": "{{orderUrl}}/details?orderId=653b6acb",
							"host": [
								"{{orderUrl}}"
							],
							"path": [
								"details"
							],
							"query": [
								{
									"key": "orderId",
									"value": "653b6acb"
								}
							]
						}
					},
					"status": "Bad Request",
					"code": 400,
					"_postman_previewlanguage": "json",
					"header": [
						{
							"key": "X-Powered-By",
							"value": "Express"
						},
						{
							"key": "Access-Control-Allow-Origin",
							"value": "*"
						},
						{
							"key": "Access-Control-Allow-Methods",
							"value": "OPTIONS, GET, POST, PUT, PATCH, DELETE"
						},
						{
							"key": "Access-Control-Allow-Headers",
							"value": "Content-Type, Authorization"
						},
						{
							"key": "Content-Type",
							"value": "application/json; charset=utf-8"
						},
						{
							"key": "Content-Length",
							"value": "31"
						},
						{
							"key": "ETag",
							"value": "W/\"1f-hXr48JXw9+c1abn9e3ChGFhAs70\""
						},
						{
							"key": "Date",
							"value": "Mon, 30 Oct 2023 13:48:15 GMT"
						},
						{
							"key": "Connection",
							"value": "keep-alive"
						},
						{
							"key": "Keep-Alive",
							"value": "timeout=5"
						}
					],
					"cookie": [],
					"body": "{\n    \"message\": \"Validation Failed\"\n}"
				}
			]
		},
		{
			"name": "admin orders",
			"request": {
				"method": "GET",
				"header": [],
				"url": {
					"raw": "{{orderUrl}}admin/list",
					"host": [
						"{{orderUrl}}admin"
					],
					"path": [
						"list"
					]
				}
			},
			"response": [
				{
					"name": "get all orders",
					"originalRequest": {
						"method": "GET",
						"header": [],
						"url": {
							"raw": "{{orderUrl}}admin/list",
							"host": [
								"{{orderUrl}}admin"
							],
							"path": [
								"list"
							]
						}
					},
					"status": "OK",
					"code": 200,
					"_postman_previewlanguage": "json",
					"header": [
						{
							"key": "X-Powered-By",
							"value": "Express"
						},
						{
							"key": "Access-Control-Allow-Origin",
							"value": "*"
						},
						{
							"key": "Access-Control-Allow-Methods",
							"value": "OPTIONS, GET, POST, PUT, PATCH, DELETE"
						},
						{
							"key": "Access-Control-Allow-Headers",
							"value": "Content-Type, Authorization"
						},
						{
							"key": "Content-Type",
							"value": "application/json; charset=utf-8"
						},
						{
							"key": "Content-Length",
							"value": "1366"
						},
						{
							"key": "ETag",
							"value": "W/\"556-Wkx5EyseavtLmaJ9/Yr/F8PIGiU\""
						},
						{
							"key": "Date",
							"value": "Fri, 27 Oct 2023 09:09:33 GMT"
						},
						{
							"key": "Connection",
							"value": "keep-alive"
						},
						{
							"key": "Keep-Alive",
							"value": "timeout=5"
						}
					],
					"cookie": [],
					"body": "[\n    {\n        \"_id\": \"653b6acbf54a7676d5e143b7\",\n        \"orderItems\": [\n            {\n                \"_id\": \"653a6fe75779169ab6a16405\",\n                \"quantity\": 1,\n                \"itemName\": \"Grilled Salmon\"\n            },\n            {\n                \"_id\": \"653a9e2daccc6e36775ff298\",\n                \"quantity\": 1,\n                \"itemName\": \"Cheesecake\"\n            },\n            {\n                \"_id\": \"653aa157accc6e36775ff29e\",\n                \"quantity\": 2,\n                \"itemName\": \"Ice Tea\"\n            }\n        ],\n        \"userId\": \"6539fae9bc694f8bcfce6629\",\n        \"status\": \"pending\",\n        \"totalPrice\": 31,\n        \"dateOrdered\": \"2023-10-27T06:47:09.513Z\",\n        \"userEmail\": \"mounayercharbel07@gmail.com\",\n        \"userAddress\": \"zook mosbeh\",\n        \"branchName\": \"Zook Branch\"\n    },\n    {\n        \"_id\": \"653b6c0cf54a7676d5e143bd\",\n        \"orderItems\": [\n            {\n                \"_id\": \"653a71545779169ab6a1640b\",\n                \"quantity\": 2,\n                \"itemName\": \"Chicken Alfredo Pasta\"\n            },\n            {\n                \"_id\": \"653aa255accc6e36775ff2a1\",\n                \"quantity\": 2,\n                \"itemName\": \"Coca-Cola\"\n            }\n        ],\n        \"userId\": \"6539fae9bc694f8bcfce6629\",\n        \"status\": \"canceled\",\n        \"totalPrice\": 36,\n        \"dateOrdered\": \"2023-10-27T08:27:50.404Z\",\n        \"userEmail\": \"mounayercharbel07@gmail.com\",\n        \"userAddress\": \"zook mosbeh\",\n        \"branchName\": \"Zook Branch\"\n    },\n    {\n        \"_id\": \"653b7bc4f54a7676d5e14405\",\n        \"orderItems\": [\n            {\n                \"_id\": \"653a6e995779169ab6a163fc\",\n                \"quantity\": 2,\n                \"itemName\": \"Mozzarella Sticks\"\n            },\n            {\n                \"_id\": \"653aa255accc6e36775ff2a1\",\n                \"quantity\": 1,\n                \"itemName\": \"Coca-Cola\"\n            },\n            {\n                \"_id\": \"653a9dddaccc6e36775ff295\",\n                \"quantity\": 1,\n                \"itemName\": \"Chocolate cake\"\n            }\n        ],\n        \"userId\": \"653ab5765d8105eb1342fd5e\",\n        \"status\": \"pending\",\n        \"totalPrice\": 27,\n        \"dateOrdered\": \"2023-10-27T06:47:09.513Z\",\n        \"userEmail\": \"elie2m@hotmail.com\",\n        \"userAddress\": \"Jdeideh\",\n        \"branchName\": \"Jdeideh Branch\"\n    }\n]"
				},
				{
					"name": "filter by orderId",
					"originalRequest": {
						"method": "GET",
						"header": [],
						"url": {
							"raw": "{{orderUrl}}admin/list?orderId=653b7bc4f54a7676d5e14405",
							"host": [
								"{{orderUrl}}admin"
							],
							"path": [
								"list"
							],
							"query": [
								{
									"key": "orderId",
									"value": "653b7bc4f54a7676d5e14405"
								}
							]
						}
					},
					"status": "OK",
					"code": 200,
					"_postman_previewlanguage": "json",
					"header": [
						{
							"key": "X-Powered-By",
							"value": "Express"
						},
						{
							"key": "Access-Control-Allow-Origin",
							"value": "*"
						},
						{
							"key": "Access-Control-Allow-Methods",
							"value": "OPTIONS, GET, POST, PUT, PATCH, DELETE"
						},
						{
							"key": "Access-Control-Allow-Headers",
							"value": "Content-Type, Authorization"
						},
						{
							"key": "Content-Type",
							"value": "application/json; charset=utf-8"
						},
						{
							"key": "Content-Length",
							"value": "476"
						},
						{
							"key": "ETag",
							"value": "W/\"1dc-0vYfrUPjPJJdzv0Yku3C6eO8dtE\""
						},
						{
							"key": "Date",
							"value": "Fri, 27 Oct 2023 09:13:27 GMT"
						},
						{
							"key": "Connection",
							"value": "keep-alive"
						},
						{
							"key": "Keep-Alive",
							"value": "timeout=5"
						}
					],
					"cookie": [],
					"body": "[\n    {\n        \"_id\": \"653b7bc4f54a7676d5e14405\",\n        \"orderItems\": [\n            {\n                \"_id\": \"653a6e995779169ab6a163fc\",\n                \"quantity\": 2,\n                \"itemName\": \"Mozzarella Sticks\"\n            },\n            {\n                \"_id\": \"653aa255accc6e36775ff2a1\",\n                \"quantity\": 1,\n                \"itemName\": \"Coca-Cola\"\n            },\n            {\n                \"_id\": \"653a9dddaccc6e36775ff295\",\n                \"quantity\": 1,\n                \"itemName\": \"Chocolate cake\"\n            }\n        ],\n        \"userId\": \"653ab5765d8105eb1342fd5e\",\n        \"status\": \"pending\",\n        \"totalPrice\": 27,\n        \"dateOrdered\": \"2023-10-27T06:47:09.513Z\",\n        \"userEmail\": \"elie2m@hotmail.com\",\n        \"userAddress\": \"Jdeideh\",\n        \"branchName\": \"Jdeideh Branch\"\n    }\n]"
				},
				{
					"name": "validation failed",
					"originalRequest": {
						"method": "GET",
						"header": [],
						"url": {
							"raw": "{{orderUrl}}admin/list?orderId=653b7bc4f54a7",
							"host": [
								"{{orderUrl}}admin"
							],
							"path": [
								"list"
							],
							"query": [
								{
									"key": "orderId",
									"value": "653b7bc4f54a7"
								}
							]
						}
					},
					"status": "Bad Request",
					"code": 400,
					"_postman_previewlanguage": "json",
					"header": [
						{
							"key": "X-Powered-By",
							"value": "Express"
						},
						{
							"key": "Access-Control-Allow-Origin",
							"value": "*"
						},
						{
							"key": "Access-Control-Allow-Methods",
							"value": "OPTIONS, GET, POST, PUT, PATCH, DELETE"
						},
						{
							"key": "Access-Control-Allow-Headers",
							"value": "Content-Type, Authorization"
						},
						{
							"key": "Content-Type",
							"value": "application/json; charset=utf-8"
						},
						{
							"key": "Content-Length",
							"value": "31"
						},
						{
							"key": "ETag",
							"value": "W/\"1f-hXr48JXw9+c1abn9e3ChGFhAs70\""
						},
						{
							"key": "Date",
							"value": "Mon, 30 Oct 2023 13:49:25 GMT"
						},
						{
							"key": "Connection",
							"value": "keep-alive"
						},
						{
							"key": "Keep-Alive",
							"value": "timeout=5"
						}
					],
					"cookie": [],
					"body": "{\n    \"message\": \"Validation Failed\"\n}"
				}
			]
		},
		{
			"name": "update  order",
			"request": {
				"method": "PUT",
				"header": [],
				"body": {
					"mode": "raw",
					"raw": "{\r\n     \"orderItems\":[{\"_id\":\"653a71545779169ab6a1640b\",\"quantity\":2},{\"_id\":\"653aa255accc6e36775ff2a1\",\"quantity\":2}]\r\n}",
					"options": {
						"raw": {
							"language": "json"
						}
					}
				},
				"url": {
					"raw": "{{orderUrl}}?orderId=653b6c0cf54a7676d5e143bd",
					"host": [
						"{{orderUrl}}"
					],
					"query": [
						{
							"key": "orderId",
							"value": "653b6c0cf54a7676d5e143bd"
						}
					]
				}
			},
			"response": [
				{
					"name": "Successfully updating order",
					"originalRequest": {
						"method": "PUT",
						"header": [],
						"body": {
							"mode": "raw",
							"raw": "{\r\n     \"orderItems\":[{\"_id\":\"653a71545779169ab6a1640b\",\"quantity\":2},{\"_id\":\"653aa255accc6e36775ff2a1\",\"quantity\":2}]\r\n}",
							"options": {
								"raw": {
									"language": "json"
								}
							}
						},
						"url": {
							"raw": "{{orderUrl}}?orderId=653b6c0cf54a7676d5e143bd",
							"host": [
								"{{orderUrl}}"
							],
							"query": [
								{
									"key": "orderId",
									"value": "653b6c0cf54a7676d5e143bd"
								}
							]
						}
					},
					"status": "OK",
					"code": 200,
					"_postman_previewlanguage": "json",
					"header": [
						{
							"key": "X-Powered-By",
							"value": "Express"
						},
						{
							"key": "Access-Control-Allow-Origin",
							"value": "*"
						},
						{
							"key": "Access-Control-Allow-Methods",
							"value": "OPTIONS, GET, POST, PUT, PATCH, DELETE"
						},
						{
							"key": "Access-Control-Allow-Headers",
							"value": "Content-Type, Authorization"
						},
						{
							"key": "Content-Type",
							"value": "application/json; charset=utf-8"
						},
						{
							"key": "Content-Length",
							"value": "400"
						},
						{
							"key": "ETag",
							"value": "W/\"190-7Liftm/tufYEpI0PlT+N2q3Zo24\""
						},
						{
							"key": "Date",
							"value": "Fri, 27 Oct 2023 08:27:50 GMT"
						},
						{
							"key": "Connection",
							"value": "keep-alive"
						},
						{
							"key": "Keep-Alive",
							"value": "timeout=5"
						}
					],
					"cookie": [],
					"body": "{\n    \"_id\": \"653b6c0cf54a7676d5e143bd\",\n    \"orderItems\": [\n        {\n            \"_id\": \"653a71545779169ab6a1640b\",\n            \"quantity\": 2,\n            \"itemName\": \"Chicken Alfredo Pasta\"\n        },\n        {\n            \"_id\": \"653aa255accc6e36775ff2a1\",\n            \"quantity\": 2,\n            \"itemName\": \"Coca-Cola\"\n        }\n    ],\n    \"userId\": \"6539fae9bc694f8bcfce6629\",\n    \"addressId\": \"653aa5a6accc6e36775ff2a3\",\n    \"branchId\": \"653b61e2f54a7676d5e14394\",\n    \"status\": \"pending\",\n    \"totalPrice\": 36,\n    \"dateOrdered\": \"2023-10-27T08:27:50.404Z\",\n    \"__v\": 1\n}"
				},
				{
					"name": "validation failed",
					"originalRequest": {
						"method": "PUT",
						"header": [],
						"body": {
							"mode": "raw",
							"raw": "{\r\n     \"orderItems\":[{\"_id\":\"653a71545779169ab6a1640b\",\"quantity\":0},{\"_id\":\"653aa255accc6e36775ff2a1\",\"quantity\":2}]\r\n}",
							"options": {
								"raw": {
									"language": "json"
								}
							}
						},
						"url": {
							"raw": "{{orderUrl}}?orderId=653b6c0cf54a7676d5e143bd",
							"host": [
								"{{orderUrl}}"
							],
							"query": [
								{
									"key": "orderId",
									"value": "653b6c0cf54a7676d5e143bd"
								}
							]
						}
					},
					"status": "Bad Request",
					"code": 400,
					"_postman_previewlanguage": "json",
					"header": [
						{
							"key": "X-Powered-By",
							"value": "Express"
						},
						{
							"key": "Access-Control-Allow-Origin",
							"value": "*"
						},
						{
							"key": "Access-Control-Allow-Methods",
							"value": "OPTIONS, GET, POST, PUT, PATCH, DELETE"
						},
						{
							"key": "Access-Control-Allow-Headers",
							"value": "Content-Type, Authorization"
						},
						{
							"key": "Content-Type",
							"value": "application/json; charset=utf-8"
						},
						{
							"key": "Content-Length",
							"value": "31"
						},
						{
							"key": "ETag",
							"value": "W/\"1f-hXr48JXw9+c1abn9e3ChGFhAs70\""
						},
						{
							"key": "Date",
							"value": "Mon, 30 Oct 2023 13:49:57 GMT"
						},
						{
							"key": "Connection",
							"value": "keep-alive"
						},
						{
							"key": "Keep-Alive",
							"value": "timeout=5"
						}
					],
					"cookie": [],
					"body": "{\n    \"message\": \"Validation Failed\"\n}"
				}
			]
		},
		{
			"name": "Accept or reject order",
			"request": {
				"method": "GET",
				"header": []
			},
			"response": [
				{
					"name": "accept order",
					"originalRequest": {
						"method": "PUT",
						"header": [],
						"url": {
							"raw": "{{orderUrl}}/accept?orderId=653b6c0cf54a7676d5e143bd",
							"host": [
								"{{orderUrl}}"
							],
							"path": [
								"accept"
							],
							"query": [
								{
									"key": "orderId",
									"value": "653b6c0cf54a7676d5e143bd"
								}
							]
						}
					},
					"status": "OK",
					"code": 200,
					"_postman_previewlanguage": "json",
					"header": [
						{
							"key": "X-Powered-By",
							"value": "Express"
						},
						{
							"key": "Access-Control-Allow-Origin",
							"value": "*"
						},
						{
							"key": "Access-Control-Allow-Methods",
							"value": "OPTIONS, GET, POST, PUT, PATCH, DELETE"
						},
						{
							"key": "Access-Control-Allow-Headers",
							"value": "Content-Type, Authorization"
						},
						{
							"key": "Content-Type",
							"value": "application/json; charset=utf-8"
						},
						{
							"key": "Content-Length",
							"value": "92"
						},
						{
							"key": "ETag",
							"value": "W/\"5c-XE4LqSKK8lMBgnDPfq7vp2yCSG8\""
						},
						{
							"key": "Date",
							"value": "Fri, 27 Oct 2023 08:33:44 GMT"
						},
						{
							"key": "Connection",
							"value": "keep-alive"
						},
						{
							"key": "Keep-Alive",
							"value": "timeout=5"
						}
					],
					"cookie": [],
					"body": "{\n    \"acknowledged\": true,\n    \"modifiedCount\": 1,\n    \"upsertedId\": null,\n    \"upsertedCount\": 0,\n    \"matchedCount\": 1\n}"
				},
				{
					"name": "reject order",
					"originalRequest": {
						"method": "PUT",
						"header": [],
						"url": {
							"raw": "{{orderUrl}}/reject?orderId=653b6c0cf54a7676d5e143bd",
							"host": [
								"{{orderUrl}}"
							],
							"path": [
								"reject"
							],
							"query": [
								{
									"key": "orderId",
									"value": "653b6c0cf54a7676d5e143bd"
								}
							]
						}
					},
					"status": "OK",
					"code": 200,
					"_postman_previewlanguage": "json",
					"header": [
						{
							"key": "X-Powered-By",
							"value": "Express"
						},
						{
							"key": "Access-Control-Allow-Origin",
							"value": "*"
						},
						{
							"key": "Access-Control-Allow-Methods",
							"value": "OPTIONS, GET, POST, PUT, PATCH, DELETE"
						},
						{
							"key": "Access-Control-Allow-Headers",
							"value": "Content-Type, Authorization"
						},
						{
							"key": "Content-Type",
							"value": "application/json; charset=utf-8"
						},
						{
							"key": "Content-Length",
							"value": "92"
						},
						{
							"key": "ETag",
							"value": "W/\"5c-XE4LqSKK8lMBgnDPfq7vp2yCSG8\""
						},
						{
							"key": "Date",
							"value": "Fri, 27 Oct 2023 08:34:56 GMT"
						},
						{
							"key": "Connection",
							"value": "keep-alive"
						},
						{
							"key": "Keep-Alive",
							"value": "timeout=5"
						}
					],
					"cookie": [],
					"body": "{\n    \"acknowledged\": true,\n    \"modifiedCount\": 1,\n    \"upsertedId\": null,\n    \"upsertedCount\": 0,\n    \"matchedCount\": 1\n}"
				},
				{
					"name": "reject canceled order",
					"originalRequest": {
						"method": "PUT",
						"header": [],
						"url": {
							"raw": "{{orderUrl}}/reject?orderId=653b6c0cf54a7676d5e143bd",
							"host": [
								"{{orderUrl}}"
							],
							"path": [
								"reject"
							],
							"query": [
								{
									"key": "orderId",
									"value": "653b6c0cf54a7676d5e143bd"
								}
							]
						}
					},
					"status": "OK",
					"code": 200,
					"_postman_previewlanguage": "json",
					"header": [
						{
							"key": "X-Powered-By",
							"value": "Express"
						},
						{
							"key": "Access-Control-Allow-Origin",
							"value": "*"
						},
						{
							"key": "Access-Control-Allow-Methods",
							"value": "OPTIONS, GET, POST, PUT, PATCH, DELETE"
						},
						{
							"key": "Access-Control-Allow-Headers",
							"value": "Content-Type, Authorization"
						},
						{
							"key": "Content-Type",
							"value": "application/json; charset=utf-8"
						},
						{
							"key": "Content-Length",
							"value": "92"
						},
						{
							"key": "ETag",
							"value": "W/\"5c-1LCrZulBgUWq5mxCUtrw/peBHVs\""
						},
						{
							"key": "Date",
							"value": "Fri, 27 Oct 2023 08:46:26 GMT"
						},
						{
							"key": "Connection",
							"value": "keep-alive"
						},
						{
							"key": "Keep-Alive",
							"value": "timeout=5"
						}
					],
					"cookie": [],
					"body": "{\n    \"acknowledged\": true,\n    \"modifiedCount\": 0,\n    \"upsertedId\": null,\n    \"upsertedCount\": 0,\n    \"matchedCount\": 0\n}"
				},
				{
					"name": "accept canceled order",
					"originalRequest": {
						"method": "PUT",
						"header": [],
						"url": {
							"raw": "{{orderUrl}}/accept?orderId=653b6c0cf54a7676d5e143bd",
							"host": [
								"{{orderUrl}}"
							],
							"path": [
								"accept"
							],
							"query": [
								{
									"key": "orderId",
									"value": "653b6c0cf54a7676d5e143bd"
								}
							]
						}
					},
					"status": "OK",
					"code": 200,
					"_postman_previewlanguage": "json",
					"header": [
						{
							"key": "X-Powered-By",
							"value": "Express"
						},
						{
							"key": "Access-Control-Allow-Origin",
							"value": "*"
						},
						{
							"key": "Access-Control-Allow-Methods",
							"value": "OPTIONS, GET, POST, PUT, PATCH, DELETE"
						},
						{
							"key": "Access-Control-Allow-Headers",
							"value": "Content-Type, Authorization"
						},
						{
							"key": "Content-Type",
							"value": "application/json; charset=utf-8"
						},
						{
							"key": "Content-Length",
							"value": "92"
						},
						{
							"key": "ETag",
							"value": "W/\"5c-1LCrZulBgUWq5mxCUtrw/peBHVs\""
						},
						{
							"key": "Date",
							"value": "Fri, 27 Oct 2023 08:48:56 GMT"
						},
						{
							"key": "Connection",
							"value": "keep-alive"
						},
						{
							"key": "Keep-Alive",
							"value": "timeout=5"
						}
					],
					"cookie": [],
					"body": "{\n    \"acknowledged\": true,\n    \"modifiedCount\": 0,\n    \"upsertedId\": null,\n    \"upsertedCount\": 0,\n    \"matchedCount\": 0\n}"
				},
				{
					"name": "validation failed",
					"originalRequest": {
						"method": "PUT",
						"header": [],
						"url": {
							"raw": "{{orderUrl}}/accept?orderId=653b6c0cf54a",
							"host": [
								"{{orderUrl}}"
							],
							"path": [
								"accept"
							],
							"query": [
								{
									"key": "orderId",
									"value": "653b6c0cf54a"
								}
							]
						}
					},
					"status": "Bad Request",
					"code": 400,
					"_postman_previewlanguage": "json",
					"header": [
						{
							"key": "X-Powered-By",
							"value": "Express"
						},
						{
							"key": "Access-Control-Allow-Origin",
							"value": "*"
						},
						{
							"key": "Access-Control-Allow-Methods",
							"value": "OPTIONS, GET, POST, PUT, PATCH, DELETE"
						},
						{
							"key": "Access-Control-Allow-Headers",
							"value": "Content-Type, Authorization"
						},
						{
							"key": "Content-Type",
							"value": "application/json; charset=utf-8"
						},
						{
							"key": "Content-Length",
							"value": "31"
						},
						{
							"key": "ETag",
							"value": "W/\"1f-hXr48JXw9+c1abn9e3ChGFhAs70\""
						},
						{
							"key": "Date",
							"value": "Mon, 30 Oct 2023 13:50:28 GMT"
						},
						{
							"key": "Connection",
							"value": "keep-alive"
						},
						{
							"key": "Keep-Alive",
							"value": "timeout=5"
						}
					],
					"cookie": [],
					"body": "{\n    \"message\": \"Validation Failed\"\n}"
				}
			]
		},
		{
			"name": "cancel order",
			"request": {
				"method": "PUT",
				"header": [],
				"url": {
					"raw": "{{orderUrl}}/cancel?orderId=653b6c0cf54a7676d5e143bd",
					"host": [
						"{{orderUrl}}"
					],
					"path": [
						"cancel"
					],
					"query": [
						{
							"key": "orderId",
							"value": "653b6c0cf54a7676d5e143bd"
						}
					]
				}
			},
			"response": [
				{
					"name": "cancel rejected order",
					"originalRequest": {
						"method": "PUT",
						"header": [],
						"url": {
							"raw": "{{orderUrl}}/cancel?orderId=653b6c0cf54a7676d5e143bd",
							"host": [
								"{{orderUrl}}"
							],
							"path": [
								"cancel"
							],
							"query": [
								{
									"key": "orderId",
									"value": "653b6c0cf54a7676d5e143bd"
								}
							]
						}
					},
					"status": "OK",
					"code": 200,
					"_postman_previewlanguage": "json",
					"header": [
						{
							"key": "X-Powered-By",
							"value": "Express"
						},
						{
							"key": "Access-Control-Allow-Origin",
							"value": "*"
						},
						{
							"key": "Access-Control-Allow-Methods",
							"value": "OPTIONS, GET, POST, PUT, PATCH, DELETE"
						},
						{
							"key": "Access-Control-Allow-Headers",
							"value": "Content-Type, Authorization"
						},
						{
							"key": "Content-Type",
							"value": "application/json; charset=utf-8"
						},
						{
							"key": "Content-Length",
							"value": "92"
						},
						{
							"key": "ETag",
							"value": "W/\"5c-1LCrZulBgUWq5mxCUtrw/peBHVs\""
						},
						{
							"key": "Date",
							"value": "Fri, 27 Oct 2023 08:40:16 GMT"
						},
						{
							"key": "Connection",
							"value": "keep-alive"
						},
						{
							"key": "Keep-Alive",
							"value": "timeout=5"
						}
					],
					"cookie": [],
					"body": "{\n    \"acknowledged\": true,\n    \"modifiedCount\": 0,\n    \"upsertedId\": null,\n    \"upsertedCount\": 0,\n    \"matchedCount\": 0\n}"
				},
				{
					"name": "cancel pending  order",
					"originalRequest": {
						"method": "PUT",
						"header": [],
						"url": {
							"raw": "{{orderUrl}}/cancel?orderId=653b6c0cf54a7676d5e143bd",
							"host": [
								"{{orderUrl}}"
							],
							"path": [
								"cancel"
							],
							"query": [
								{
									"key": "orderId",
									"value": "653b6c0cf54a7676d5e143bd"
								}
							]
						}
					},
					"status": "OK",
					"code": 200,
					"_postman_previewlanguage": "json",
					"header": [
						{
							"key": "X-Powered-By",
							"value": "Express"
						},
						{
							"key": "Access-Control-Allow-Origin",
							"value": "*"
						},
						{
							"key": "Access-Control-Allow-Methods",
							"value": "OPTIONS, GET, POST, PUT, PATCH, DELETE"
						},
						{
							"key": "Access-Control-Allow-Headers",
							"value": "Content-Type, Authorization"
						},
						{
							"key": "Content-Type",
							"value": "application/json; charset=utf-8"
						},
						{
							"key": "Content-Length",
							"value": "92"
						},
						{
							"key": "ETag",
							"value": "W/\"5c-XE4LqSKK8lMBgnDPfq7vp2yCSG8\""
						},
						{
							"key": "Date",
							"value": "Fri, 27 Oct 2023 08:45:03 GMT"
						},
						{
							"key": "Connection",
							"value": "keep-alive"
						},
						{
							"key": "Keep-Alive",
							"value": "timeout=5"
						}
					],
					"cookie": [],
					"body": "{\n    \"acknowledged\": true,\n    \"modifiedCount\": 1,\n    \"upsertedId\": null,\n    \"upsertedCount\": 0,\n    \"matchedCount\": 1\n}"
				},
				{
					"name": "validation failed",
					"originalRequest": {
						"method": "PUT",
						"header": [],
						"url": {
							"raw": "{{orderUrl}}/cancel?orderId=653b6c0cf54a767",
							"host": [
								"{{orderUrl}}"
							],
							"path": [
								"cancel"
							],
							"query": [
								{
									"key": "orderId",
									"value": "653b6c0cf54a767"
								}
							]
						}
					},
					"status": "Bad Request",
					"code": 400,
					"_postman_previewlanguage": "json",
					"header": [
						{
							"key": "X-Powered-By",
							"value": "Express"
						},
						{
							"key": "Access-Control-Allow-Origin",
							"value": "*"
						},
						{
							"key": "Access-Control-Allow-Methods",
							"value": "OPTIONS, GET, POST, PUT, PATCH, DELETE"
						},
						{
							"key": "Access-Control-Allow-Headers",
							"value": "Content-Type, Authorization"
						},
						{
							"key": "Content-Type",
							"value": "application/json; charset=utf-8"
						},
						{
							"key": "Content-Length",
							"value": "31"
						},
						{
							"key": "ETag",
							"value": "W/\"1f-hXr48JXw9+c1abn9e3ChGFhAs70\""
						},
						{
							"key": "Date",
							"value": "Mon, 30 Oct 2023 13:51:03 GMT"
						},
						{
							"key": "Connection",
							"value": "keep-alive"
						},
						{
							"key": "Keep-Alive",
							"value": "timeout=5"
						}
					],
					"cookie": [],
					"body": "{\n    \"message\": \"Validation Failed\"\n}"
				}
			]
		},
		{
			"name": "get history",
			"request": {
				"method": "GET",
				"header": [],
				"url": {
					"raw": "{{orderUrl}}history",
					"host": [
						"{{orderUrl}}history"
					]
				}
			},
			"response": [
				{
					"name": "get the orders history",
					"originalRequest": {
						"method": "GET",
						"header": [],
						"url": {
							"raw": "{{orderUrl}}history",
							"host": [
								"{{orderUrl}}history"
							]
						}
					},
					"status": "OK",
					"code": 200,
					"_postman_previewlanguage": "json",
					"header": [
						{
							"key": "X-Powered-By",
							"value": "Express"
						},
						{
							"key": "Access-Control-Allow-Origin",
							"value": "*"
						},
						{
							"key": "Access-Control-Allow-Methods",
							"value": "OPTIONS, GET, POST, PUT, PATCH, DELETE"
						},
						{
							"key": "Access-Control-Allow-Headers",
							"value": "Content-Type, Authorization"
						},
						{
							"key": "Content-Type",
							"value": "application/json; charset=utf-8"
						},
						{
							"key": "Content-Length",
							"value": "403"
						},
						{
							"key": "ETag",
							"value": "W/\"193-+9lQSHchlSqfG1N1MiGA+JYI/XE\""
						},
						{
							"key": "Date",
							"value": "Mon, 30 Oct 2023 10:02:46 GMT"
						},
						{
							"key": "Connection",
							"value": "keep-alive"
						},
						{
							"key": "Keep-Alive",
							"value": "timeout=5"
						}
					],
					"cookie": [],
					"body": "[\n    {\n        \"_id\": \"653b6c0cf54a7676d5e143bd\",\n        \"orderItems\": [\n            {\n                \"_id\": \"653a71545779169ab6a1640b\",\n                \"quantity\": 2,\n                \"itemName\": \"Chicken Alfredo Pasta\"\n            },\n            {\n                \"_id\": \"653aa255accc6e36775ff2a1\",\n                \"quantity\": 2,\n                \"itemName\": \"Coca-Cola\"\n            }\n        ],\n        \"userId\": \"6539fae9bc694f8bcfce6629\",\n        \"addressId\": \"653aa5a6accc6e36775ff2a3\",\n        \"branchId\": \"653b61e2f54a7676d5e14394\",\n        \"status\": \"canceled\",\n        \"totalPrice\": 36,\n        \"dateOrdered\": \"2023-10-27T08:27:50.404Z\",\n        \"__v\": 1\n    }\n]"
				}
			]
		}
	],
	"variable": [
		{
			"key": "orderUrl",
			"value": "http://localhost:8080/order/"
		}
	]
}